ardmediathek/__init__.py
ardmediathek/broadcast.py
ardmediathek/exceptions.py
ardmediathek/image.py
ardmediathek/program.py
ardmediathek/station.py
ardmediathek/stream.py
ardmediathek/urls.py
ardmediathek/utils.py
ardmediathek-1.2.0.dist-info/LICENSE
ardmediathek-1.2.0.dist-info/METADATA
ardmediathek-1.2.0.dist-info/WHEEL
ardmediathek-1.2.0.dist-info/top_level.txt
ardmediathek-1.2.0.dist-info/RECORD
