Metadata-Version: 2.2
Name: ardmediathek
Version: 1.2.0
Summary: Client library for the ardmediathek.de API
Home-page: https://github.com/TheFGFSEagle/ardmediathek-api
Author: TheFGFSEagle
Author-email: thefgfseagle@gmail.com
License: GPLv3
Project-URL: Homepage, https://github.com/TheFGFSEagle/ardmediathek-api
Project-URL: Bug Tracker, https://github.com/TheFGFSEagle/ardmediathek-api/issues
Keywords: ardmediathek api
Classifier: Programming Language :: Python :: 3
License-File: LICENSE
Requires-Dist: plum-dispatch
Requires-Dist: tqdm
Requires-Dist: requests
Requires-Dist: requests-cache
Requires-Dist: appdirs
Requires-Dist: bs4
Requires-Dist: Pillow
Requires-Dist: python-dateutil
Requires-Dist: natsort
Requires-Dist: lxml
